<TestData>
  <TestDataRow>
    <comment>2 samples, each of dimension 1 (e.g., (cs.price), (cs.mileage))</comment>
    <skylineSampleSQL>SELECT * FROM cars_small cs SKYLINE OF cs.price LOW, cs.mileage LOW SAMPLE BY RANDOM_SUBSETS COUNT 2 DIMENSION 1</skylineSampleSQL>
    <useSubspaces>
      <subspace>
        <equivalentToSkyline>SELECT * FROM cars_small cs SKYLINE OF cs.price LOW</equivalentToSkyline>
      </subspace>
      <subspace>
        <equivalentToSkyline>SELECT * FROM cars_small cs SKYLINE OF cs.mileage LOW</equivalentToSkyline>
      </subspace>
    </useSubspaces>
    <expectedNumberOfEntireSkylineObjects>6</expectedNumberOfEntireSkylineObjects>
  </TestDataRow>
   <TestDataRow>
    <comment>3 samples, each of dimension 2 (e.g., (cs.price, cs.mileage), (cs.mileage, cs.horsepower), (cs.price, cs.horsepower))</comment>
    <skylineSampleSQL>SELECT * FROM cars_small cs SKYLINE OF cs.price LOW, cs.mileage LOW, cs.horsepower HIGH SAMPLE BY RANDOM_SUBSETS COUNT 3 DIMENSION 2</skylineSampleSQL>
    <useSubspaces>
      <subspace>
        <equivalentToSkyline>SELECT * FROM cars_small cs SKYLINE OF cs.price LOW, cs.mileage LOW</equivalentToSkyline>
      </subspace>
      <subspace>
        <equivalentToSkyline>SELECT * FROM cars_small cs SKYLINE OF cs.mileage LOW, cs.horsepower HIGH</equivalentToSkyline>
      </subspace>
      <subspace>
        <equivalentToSkyline>SELECT * FROM cars_small cs SKYLINE OF cs.price LOW, cs.horsepower HIGH</equivalentToSkyline>
      </subspace>
    </useSubspaces>
    <expectedNumberOfEntireSkylineObjects>6</expectedNumberOfEntireSkylineObjects>
  </TestDataRow>
</TestData>
